term_from_nat/__init__.py
term_from_nat/__main__.py
term_from_nat/client_lite.py
term_from_nat/client_term.py
term_from_nat/mqtt_common.py
term_from_nat/pkt_common.py
term_from_nat/server_lite.py
term_from_nat/server_term.py
term_from_nat/term_from_nat.py
term_from_nat-0.1.6.data/scripts/term_from_nat_cli.py
term_from_nat-0.1.6.dist-info/LICENSE
term_from_nat-0.1.6.dist-info/METADATA
term_from_nat-0.1.6.dist-info/WHEEL
term_from_nat-0.1.6.dist-info/entry_points.txt
term_from_nat-0.1.6.dist-info/top_level.txt
term_from_nat-0.1.6.dist-info/RECORD
