Metadata-Version: 2.1
Name: term-from-nat
Version: 0.1.6
Summary: A remote term connect from one nat to another nat
Home-page: https://github.com/Jiangshan00001/term_from_nat
Author: jiangshan00000
Author-email: 710806594@qq.com
License: UNKNOWN
Platform: UNKNOWN
Classifier: Programming Language :: Python :: 3
Classifier: License :: OSI Approved :: GNU General Public License v3 (GPLv3)
Classifier: Operating System :: OS Independent
Requires-Dist: paho-mqtt
